{"names":["Fur Woman Coat","Thin Designed Woman Coat","Thin Simple Man Coat","Thick Simple Man Coat","Checked Woman Coat","Mid Man Coat","Fancy Simple Man Coat","Long Simple Woman Coat","Short Simple Woman Coat","Thin Simple Woman Coat","Fur Fancy Woman Coat","Fur Simple Woman Coat","Long Thin Simple Man Coat","Long Thin Fancy Woman Coat","Long Thin Woman Coat","Long Thin Simple Woman Coat","Long Thick Simple Man Coat","Mid Thick Simple Man Coat","Mid Fur Simple Woman Coat","Long Leather Simple Woman Coat","Short Thin Fashioned Woman Coat","Long Simple Man Coat","Long Fashioned Woman Coat","Short Thin Checked Woman Coat","Short Thick Simple Woman Coat","Mid Thick Woman Coat","Thick Cleaned Woman Coat","Thick Fancy Woman Coat","Short Designed Woman Coat","Short Fancy Man Coat","Short Simple Designed Woman Coat","Short Fancy Designed Woman Coat","Mid Clean Woman Coat","Short Fashioned Woman Coat","Striped Man Shirt","Simple Designed Woman Shirt","Open Neck Designed Woman Shirt","Center Designed Woman Shirt","Overfit Designed Woman Shirt","Smooth Cleaned Man Shirt","Designed Woman Shirt","Cleaned Man Shirt","Overfit Simple Designed Man Shirt","Center Designed Man Shirt","Striped Designed Woman Shirt","Designed Woan Shirt","Simple Tailored Man Shirt","Overfit Center Designed Woman Shirt","Fitted Designed Man Shirt","Simple Designed Man Shirt","Fancy Simple Designed Man Shirt","Designed Crop Top Woman Shirt","Fitted Fancy Simple Designed Woman Shirt","Fancy Cleaned Center Designed Man Shirt","Overfit Cleaned Back Desigend Man Shirt","Fancy Cleaned Simple Designed Woman Shirt","Thick Designed Man Hoodie","Thin Designed Woman Hoodie","Thin Simple Man Hoodie","Designed Man Hoodie","Thick Simple Woman Hoodie","Simple Man Hoodie","Thin Fancy Man Hoodie","Designed Woman Hoodie","Thin Fancy Simple Woman Hoodie","Thick Designed Woman Hoodie","Thin Designed Man Hoodie","Fancy Designed Man Hoodie","Thick Fancy Designed Woman Hoodie","Fancy Smooth Woman Hoodie","Thin Clean Woman Hoodie","Fancy Designed Woman Hoodie","Thick Smooth Man Hoodie","Fancy Clean Designed Woman Hoodie","Winter Christmas Designed Woman Sweater","Thin Cable Knit Woman Sweater","Aran Woman Sweater","Aran Crop Top Woman Sweater","Thick Aran Man Sweater","Thin Crew Neck Woman Sweater","Cowl Simple Woman Sweater","Long Neck Cashmere Man Sweater","Overfit Boyfriend Woman Sweater","Winter Christmas Woman Sweater","Crew Neck Man Sweater","Mid Boyfriend Woman Sweater","Crew Neck Fancy Woman Sweater","Aran Patterned Man Sweater","Cable Knit Crop Top Fancy Woman Sweater","Clean Designed Man to Man Sweater","Overfit Crew Neck Fancy Woman Sweater","Cowl Neck Fancy Woman Sweater","Cable Knit Three Layer Woman Sweater","Cowl Neck Cleaned Fancy Woman Sweater","Mid Cowl Neck Thin Woman Sweater"],"results":{"coat":[{"id":"1","name":"Fur Woman Coat","sale":20,"color":"brown","image":["600d43aa-7da1-4f2f-813b-eb57cbbf0880","33f8d6d6-0486-4b6f-b0f8-ad48e03ee046"],"price":240,"gender":"female","category":"coat"},{"id":"2","name":"Thin Designed Woman Coat","sale":0,"color":"red","image":["6a037b6b-ad8f-4a15-829d-73d0ad7f8273","f60476ce-5363-4344-81b6-86a6f4e08fc4","75f1ddec-0df7-4fdb-a980-0e46077d8bd3"],"price":184,"gender":"female","category":"coat"},{"id":"3","name":"Thin Designed Woman Coat","sale":0,"color":"gray","image":["af2b1510-b38a-4fd7-b271-81d022ab715c","79808e38-8927-4090-875a-be446b3cef93"],"price":184,"gender":"female","category":"coat"},{"id":"4","name":"Thin Simple Man Coat","sale":0,"color":"light brown","image":["6069e6e1-60ad-461d-b288-f69de74c5777","9d0bb2bc-c016-41ae-ad40-800c2a772b8d"],"price":200,"gender":"male","category":"coat"},{"id":"5","name":"Thick Simple Man Coat","sale":0,"color":"navy","image":["28237e94-28c4-4bcc-9c35-22e6cf709db1","e57a5b00-7f1c-4cfc-9478-115bc508d667"],"price":136,"gender":"male","category":"coat"},{"id":"6","name":"Checked Woman Coat","sale":0,"color":"gray","image":["fc14acf6-633d-40e7-940e-28d00ee6d8c5","cff70745-6943-452b-bfd4-c85a0ac64cfa"],"price":250,"gender":"female","category":"coat"},{"id":"7","name":"Mid Man Coat","sale":0,"color":"light brown","image":["2150329b-ebe1-45b8-a54e-c0c9be296f2a","c7623918-c571-44ae-9560-f24ecc06be29","bebbb8c1-a6fb-4ac5-9f8c-8593dd2127a1"],"price":184,"gender":"male","category":"coat"},{"id":"8","name":"Fancy Simple Man Coat","sale":25,"color":"brown","image":["0e1a335b-034b-4136-867e-8c67789cb232","afa9c0b5-c605-4c15-9557-d85e77a1cd9a","26bd7608-403b-42e1-ab5c-554e366eb56a"],"price":320,"gender":"male","category":"coat"},{"id":"9","name":"Long Simple Woman Coat","sale":0,"color":"brown","image":["8b157ad7-c47b-420c-8ea3-1900f0175bb9","5dcdb7a6-94ac-4a6f-b44c-10f2b5361565"],"price":200,"gender":"female","category":"coat"},{"id":"10","name":"Short Simple Woman Coat","sale":10,"color":"green","image":["7540cf5c-9c0b-4d08-8a63-7e76400d16e4","ed4458d3-1800-4fae-8427-6f71ff4f729d"],"price":160,"gender":"female","category":"coat"},{"id":"11","name":"Short Simple Woman Coat","sale":0,"color":"brown","image":["3d15d602-ceed-4086-8906-c9334056a77a","3f81aee9-22aa-49e8-abdb-40b6cb6180c3"],"price":170,"gender":"female","category":"coat"},{"id":"12","name":"Thin Simple Woman Coat","sale":10,"color":"pink","image":["d2bfc898-9f68-4654-9ce0-e30776ce46e8","833e31d2-1e3c-494d-90d8-c212737c0450","43376f55-ec97-4d75-a6a2-64bec12f649d"],"price":160,"gender":"female","category":"coat"},{"id":"13","name":"Fur Fancy Woman Coat","sale":0,"color":"white","image":["0fde87d6-6ca3-4de9-828b-9efa978d4ab0","c654700a-cf66-413f-a02c-d53fb9730d25","94fbb5ef-15c8-439a-b530-995a47669bf7","88633993-8d7e-4393-a06a-892ebad61a4b"],"price":340,"gender":"female","category":"coat"},{"id":"14","name":"Fur Simple Woman Coat","sale":0,"color":"red","image":["ab6846a3-8761-413e-a7ee-72e164e156a6","d6990cfc-c32f-4da7-9b14-644d88c45b40"],"price":174,"gender":"female","category":"coat"},{"id":"15","name":"Long Thin Simple Man Coat","sale":5,"color":"light brown","image":["a8ddb7f8-2cae-4d9d-907c-8c91e35fd63b","a5cbda6e-7cf0-4178-84ff-c233cadd60ba"],"price":312,"gender":"male","category":"coat"},{"id":"16","name":"Long Thin Fancy Woman Coat","sale":0,"color":"begie","image":["267e6fc1-77e2-4d6f-88c5-a915cca60a00","91c439fb-f66e-4138-a635-755961e6766f","8dfcd394-3384-44e8-a655-715fad508431","4db0cb13-f368-4230-97cd-2b0067bb1004"],"price":342,"gender":"female","category":"coat"},{"id":"17","name":"Long Thin Woman Coat","sale":0,"color":"dark green","image":["89bf74c7-af77-4875-9157-5b8ab71b9f26","781bb80c-ce98-4e8b-bd27-4d3fa85e711f"],"price":300,"gender":"female","category":"coat"},{"id":"18","name":"Long Thin Simple Woman Coat","sale":0,"color":"light brown","image":["ee748321-af3a-41fd-bba3-c90037388cb5","5fe0a5c5-8b3f-4238-a009-d63eca7d17e7","82076125-97ad-4f69-b233-aff1710f57d4"],"price":220,"gender":"female","category":"coat"},{"id":"19","name":"Long Thick Simple Man Coat","sale":5,"color":"light brown","image":["913c79c2-ce83-4bd0-97ac-e53dfd70d836","07b2b64b-365e-48f1-b0b4-af37ef6fcaeb"],"price":340,"gender":"male","category":"coat"},{"id":"20","name":"Mid Thick Simple Man Coat","sale":0,"color":"black","image":["367dadc1-000f-43db-8195-ff55e9920557","f967ff08-91fe-477c-9f6e-ea1bf97d32f3"],"price":240,"gender":"male","category":"coat"},{"id":"21","name":"Mid Fur Simple Woman Coat","sale":0,"color":"white","image":["b6ca4e40-43c9-435e-b323-9814a2018740","341eb181-6bc0-4943-8da0-fd96bdec38b5","6317d8a7-0ce1-4c39-80bd-ab5f2d0afa1d"],"price":200,"gender":"female","category":"coat"},{"id":"22","name":"Long Leather Simple Woman Coat","sale":0,"color":"brown","image":["41c07435-0b37-40e6-96c3-19b9c0574f34","411a118c-c4f1-414a-a146-116022066601","83009e0e-6c5f-49a6-8ac3-fbbc87fd00e8"],"price":280,"gender":"female","category":"coat"},{"id":"23","name":"Short Thin Fashioned Woman Coat","sale":0,"color":"green","image":["95b1f0cb-781c-437b-8cb2-b41b0b0c120c","6cd8f4e7-5d83-4334-84aa-7e03a95f770f","615a6b08-db3a-4a1d-984d-a3229dba058a"],"price":190,"gender":"female","category":"coat"},{"id":"24","name":"Long Simple Man Coat","sale":0,"color":"light brown","image":["a5168609-9212-46cf-9c6a-040d2f639c71","62425124-fd49-4e84-be7c-9795388e491b"],"price":180,"gender":"male","category":"coat"},{"id":"25","name":"Long Fashioned Woman Coat","sale":0,"color":"light red","image":["c288b3a3-6892-4f4a-a907-0a42da5691b5","5a8fb516-38de-4347-a925-07b363126dbf"],"price":240,"gender":"female","category":"coat"},{"id":"26","name":"Mid Man Coat","sale":0,"color":"yellow","image":["18cd1a13-d5b6-4fbe-a403-48d97252c594","bdfcc736-5283-4980-ba4a-c541d221a960","12a18261-a585-48d1-a81c-1056dd839e45"],"price":260,"gender":"male","category":"coat"},{"id":"27","name":"Short Simple Woman Coat","sale":0,"color":"navy","image":["d9af0907-7fb6-4dbb-ab6b-8e229758b298","c7be3f3f-0f7f-4b8b-ab99-64b3ab0e205e","77f921fe-501e-4607-8875-6cdc858803cc"],"price":160,"gender":"female","category":"coat"},{"id":"28","name":"Long Simple Woman Coat","sale":0,"color":"light blue","image":["d20ba649-e45c-4c94-b6dc-ac4bcc2a6aa5","a05665ae-24a2-49b3-bd87-a191bb6784e0","7c84ed28-0a3b-4192-8619-3bbe6a934f60"],"price":184,"gender":"female","category":"coat"},{"id":"29","name":"Short Thin Checked Woman Coat","sale":0,"color":"gray","image":["73dc8d58-16da-4cfd-8aab-f1db508148e7","cb4f4134-f0dc-4b85-b8f0-5dd12ee11476","6b69bf30-b867-4660-9024-6b60c2833d52"],"price":192,"gender":"female","category":"coat"},{"id":"30","name":"Short Thick Simple Woman Coat","sale":0,"color":"dark green","image":["2750e6d2-0da1-499f-9dea-d69974b737e4","87c857bc-e90f-4fae-a71b-d2528e440653","3c0589bc-2f4a-41b8-afff-c38e6a73f6f9"],"price":192,"gender":"female","category":"coat"},{"id":"31","name":"Mid Thick Simple Man Coat","sale":10,"color":"dark gray","image":["1263d33f-110a-4233-a60e-265a244291eb","2997bc78-eb3e-4032-abac-fc0df611a79a","00f9181d-e0e3-41d0-89da-380f5c92c81d"],"price":240,"gender":"male","category":"coat"},{"id":"32","name":"Mid Thick Woman Coat","sale":5,"color":"black","image":["529af02a-c9ca-4a26-ad28-63a1d00e9c58","45025b01-e7f8-4e62-9091-9cc6caf26da8","7eb54c0c-0de4-4feb-a5e0-cc0629a6476d","97b1ed78-1fcc-4390-bf32-b0e6caa8ad0d"],"price":220,"gender":"female","category":"coat"},{"id":"33","name":"Mid Thick Simple Man Coat","sale":0,"color":"brown","image":["fe458ccd-d5b4-4e5b-8667-2d4e36372ef1","6bfd605b-c8cf-4909-a3ae-a74ce8d0e4b1","7696ce78-6f40-4304-b045-e47402aab1b5"],"price":240,"gender":"male","category":"coat"},{"id":"34","name":"Thick Cleaned Woman Coat","sale":5,"color":"white","image":["8813f94d-37de-491f-a7c9-afe1713ea774","81cac486-8539-49be-b94f-2db3ad200b7d","ad1d147a-1daa-4b47-920a-144f04700968","7319b97f-1eab-44cf-beb8-2dfa03a1a8cb"],"price":330,"gender":"female","category":"coat"},{"id":"35","name":"Thick Fancy Woman Coat","sale":0,"color":"light brown","image":["7f7f0dfe-ebb1-4963-b07a-6dfaaea7a47a","3e68d854-4a2b-4882-bf7e-2897d04782ac","94342ad4-348d-44cc-8cf3-e73b08b29b5f","1a0427be-693e-4e75-b71d-8e44521ea38b"],"price":340,"gender":"female","category":"coat"},{"id":"36","name":"Short Designed Woman Coat","sale":0,"color":"yellow","image":["f05f746c-0144-4c96-9163-6b5ecd04abf8","639ea6c2-a45d-4de0-a560-008db686d812","282a3d3f-a07a-4227-a5b7-05a812e249f4","1b364c54-5834-4e6d-af27-4329345ccc58"],"price":280,"gender":"female","category":"coat"},{"id":"37","name":"Short Fancy Man Coat","sale":0,"color":"gray","image":["8e88f07a-6547-4ddb-b016-4aa746f68037","df046b19-0691-4634-ae76-6be21cf87f10"],"price":360,"gender":"male","category":"coat"},{"id":"38","name":"Short Simple Designed Woman Coat","sale":0,"color":"black","image":["2993a75a-a304-447e-8ea4-33112120169c","5e828133-dc77-4e7a-b787-d673395feeca","af2ebee8-9063-4c37-89b5-b20e535f3a79","afdd7a78-b76a-4ae4-9698-bb0116e83cd8","fe9e7fa9-4f6e-4859-b71d-ff79b886cc86"],"price":360,"gender":"female","category":"coat"},{"id":"39","name":"Short Fancy Designed Woman Coat","sale":5,"color":"white","image":["982694b3-d867-4137-bf5b-93ae3b8bb335","b167aa07-766a-4370-bca4-002c01095418","851f19f9-c1ab-4a1b-8b3f-19de737de4b2","32941603-8114-4327-8d4e-904341198813"],"price":380,"gender":"female","category":"coat"},{"id":"40","name":"Mid Clean Woman Coat","sale":0,"color":"white","image":["be3dc8a1-77e4-4266-ae94-f81274917937","437ef009-f539-46ea-a963-96ced9360d15","76eb2d6d-5608-48e7-a0fc-c2ed262c2e68"],"price":340,"gender":"female","category":"coat"},{"id":"41","name":"Short Fashioned Woman Coat","sale":0,"color":"black","image":["4f5d0b0a-adb9-496b-8549-f26d4c6e5dd4","05afa457-07c7-4d05-b2d1-cd4637f61a09"],"price":364,"gender":"female","category":"coat"}],"shirt":[{"id":"1","name":"Striped Man Shirt","sale":0,"color":"red","image":["a52dbd57-033f-4493-8c01-97ba1e5ebe66","9872bfce-eb74-40f8-b22c-6b9f6ef5d4e4"],"price":46,"gender":"male","category":"shirt"},{"id":"2","name":"Simple Designed Woman Shirt","sale":0,"color":"white","image":["d8a3092e-4858-4484-9cfa-97245dc2f6c1","cbe9e2c1-e52d-4cd6-b562-790402e18df9"],"price":50,"gender":"female","category":"shirt"},{"id":"3","name":"Open Neck Designed Woman Shirt","sale":25,"color":"light red","image":["cbfcdf51-7d2b-4d84-a2a2-c23d88de34da","67e34cb3-d84c-4f56-a387-21db082006de"],"price":52,"gender":"female","category":"shirt"},{"id":"4","name":"Center Designed Woman Shirt","sale":0,"color":"black","image":["ced67682-14cc-4826-9922-849c7313701c","cf765089-a698-4224-bd5a-ceefb07f6206"],"price":36,"gender":"female","category":"shirt"},{"id":"5","name":"Overfit Designed Woman Shirt","sale":0,"color":"navy","image":["13f0ddb5-e544-4148-98d9-023f41ec665f","564bfcd3-e64c-41c1-98d7-9df59cbdedcb"],"price":46,"gender":"female","category":"shirt"},{"id":"6","name":"Smooth Cleaned Man Shirt","sale":0,"color":"green","image":["cb8d411b-7540-4abf-96fc-340bfa8fb91e","a6cb393e-64ea-49a9-905e-65c8a0ab666d","99890746-4d4b-4a84-a9b1-d84545b887c2"],"price":36,"gender":"male","category":"shirt"},{"id":"7","name":"Designed Woman Shirt","sale":0,"color":"white","image":["298a0ffb-79d8-4779-a91e-a3a22a7052f3","16aa71ab-dfe1-4e6d-bc4b-84177b5c9025"],"price":30,"gender":"female","category":"shirt"},{"id":"8","name":"Cleaned Man Shirt","sale":10,"color":"white","image":["98377ff5-bc2b-4d16-94f8-60b71cbbf421","a0fb33dc-21f6-4092-8bb8-c3ae8cb2d42a","8f9617f9-c9f1-426b-b947-9102c4f8f846"],"price":30,"gender":"male","category":"shirt"},{"id":"9","name":"Overfit Simple Designed Man Shirt","sale":10,"color":"white","image":["f3156143-7d81-435b-bff1-94ec1e7236d1","55e6bf38-9983-46b8-9510-7cc3b66fa7bd"],"price":42,"gender":"male","category":"shirt"},{"id":"10","name":"Center Designed Man Shirt","sale":0,"color":"white","image":["a83f7df3-a736-4f17-b263-91a10cfdd7f1","b8da7563-0403-44da-b870-c33b78aa7464"],"price":36,"gender":"male","category":"shirt"},{"id":"11","name":"Striped Designed Woman Shirt","sale":0,"color":"begie","image":["c352c5bc-199d-4d00-846e-17becbd808e0","6a0f4179-56b2-4663-8d47-891d9ae8f5bd"],"price":54,"gender":"female","category":"shirt"},{"id":"12","name":"Designed Woan Shirt","sale":0,"color":"black","image":["4abcbe10-d4af-4605-9671-d06af7c56199","4169b64e-8385-42a0-8ff5-d20cd8ce5249","9523f7ca-74ae-4ade-892b-1c20367d6f1d"],"price":40,"gender":"female","category":"shirt"},{"id":"13","name":"Simple Tailored Man Shirt","sale":0,"color":"black","image":["b3c21c53-0de7-4949-90db-bbf2dbaeb923","419a3d34-266a-46e9-9569-b7f107b1a180"],"price":44,"gender":"male","category":"shirt"},{"id":"14","name":"Overfit Center Designed Woman Shirt","sale":0,"color":"white","image":["e669e775-44fb-4d8e-a904-91f90f66e242","79e1f3a9-1df2-422e-aac9-246498facf29"],"price":34,"gender":"female","category":"shirt"},{"id":"15","name":"Fitted Designed Man Shirt","sale":0,"color":"navy","image":["a7c6bdd7-d0aa-4fd3-b929-403815bbbdf9","64b28aa0-9d91-4d3f-a7bb-5b9b8aad725b"],"price":46,"gender":"male","category":"shirt"},{"id":"16","name":"Simple Designed Man Shirt","sale":10,"color":"white","image":["22840476-8fef-4e85-9bf4-4af1e8f73bb8","d3346326-5916-4595-97d4-fee0c60880e2"],"price":50,"gender":"male","category":"shirt"},{"id":"17","name":"Fancy Simple Designed Man Shirt","sale":10,"color":"black","image":["d331b49f-5659-4042-bd4a-636b37fe903f","e890b647-cc13-458d-bfee-6639c9aa88a4"],"price":66,"gender":"male","category":"shirt"},{"id":"18","name":"Designed Crop Top Woman Shirt","sale":10,"color":"black","image":["1a065cff-cef1-4c09-b5e1-2e98d3f30a59","8668198f-018b-4c2b-a9a9-392e2242f2b1","6d2f2cd0-eaaa-4e21-8ac6-262c66e30058"],"price":55,"gender":"female","category":"shirt"},{"id":"19","name":"Overfit Center Designed Woman Shirt","sale":0,"color":"navy","image":["a224a858-f9ca-4802-851d-ed598d7e6e19","2a596724-4ba4-46d9-bf06-946e6636c5af"],"price":50,"gender":"female","category":"shirt"},{"id":"20","name":"Fitted Fancy Simple Designed Woman Shirt","sale":10,"color":"white","image":["1774c99b-a310-4d18-abbd-2dfafaae8dea","1f03aa18-ddaa-492c-b68c-477f772d8831","c955e2a3-e7d5-400d-8353-1c2f8a2f91af"],"price":76,"gender":"female","category":"shirt"},{"id":"21","name":"Fancy Cleaned Center Designed Man Shirt","sale":0,"color":"black","image":["7bb0f757-26d0-495f-bc1b-52a615644040","6b1acc6f-46fe-4592-bdd1-16540609b89a"],"price":50,"gender":"male","category":"shirt"},{"id":"22","name":"Fancy Cleaned Center Designed Man Shirt","sale":0,"color":"white","image":["bd603dcf-1372-4c84-b2bc-70df4cef59dd","8394ada6-3b2c-4fbb-9a95-aff6fcfd451b"],"price":50,"gender":"male","category":"shirt"},{"id":"23","name":"Overfit Cleaned Back Desigend Man Shirt","sale":0,"color":"white","image":["1df2a664-958f-408c-a85a-0898ebcfb032","3f17c1ed-a3d1-49fc-b040-1eb80f70daab"],"price":56,"gender":"male","category":"shirt"},{"id":"24","name":"Fancy Cleaned Simple Designed Woman Shirt","sale":0,"color":"black","image":["fee6f631-73d8-43b5-906b-824603b51777","a25ef957-686a-4206-a8fd-61393225d155","47fc3520-24a1-4da4-8367-607df6940170"],"price":60,"gender":"female","category":"shirt"}],"hoodie":[{"id":"1","name":"Thick Designed Man Hoodie","sale":0,"color":"navy","image":["02d82990-d18c-456c-a62d-7ece336619dd","8984bd8a-298d-4bb6-9538-a9d38050cb46"],"price":90,"gender":"male","category":"hoodie"},{"id":"2","name":"Thin Designed Woman Hoodie","sale":0,"color":"white","image":["3e0423f1-035e-4596-8b11-5493420eb8c0","bbfa563e-6064-44d7-8309-825a4fc5696f","e8eb1187-775e-47c2-aeba-ef0f9cc81d1e"],"price":76,"gender":"female","category":"hoodie"},{"id":"3","name":"Thin Simple Man Hoodie","sale":0,"color":"light blue","image":["cff52b4d-e44c-4f89-a03e-a3dce782d947","2907d4aa-9214-4b8a-8aaa-6c2a30030e6f","7991462d-378e-4fcb-b7f6-d0d99c9bbac7"],"price":60,"gender":"male","category":"hoodie"},{"id":"4","name":"Designed Man Hoodie","sale":0,"color":"pink","image":["cdadf8fc-4b0f-47d7-a78c-8bc60bf22979","8f41063f-aef1-4664-bd2e-a2015b5b87f4","e0bf8c11-6fc0-44f3-8153-5256e0a39e5d"],"price":68,"gender":"male","category":"hoodie"},{"id":"5","name":"Thick Simple Woman Hoodie","sale":10,"color":"gray","image":["0e5da30f-99bb-4d2d-9f5a-e83dd03ff1ec","50703f37-ad58-4eaf-a10a-342fadae2651"],"price":70,"gender":"female","category":"hoodie"},{"id":"6","name":"Thick Simple Woman Hoodie","sale":10,"color":"red","image":["26e4bb88-d03f-4645-b6c7-99e6eb5e9f0c","5fe02ba8-fa98-497b-86c3-ea3370200e18","8b15311e-3f4d-4fe3-942a-93fdfe09703c"],"price":70,"gender":"female","category":"hoodie"},{"id":"7","name":"Simple Man Hoodie","sale":0,"color":"white","image":["bbff293b-b5da-4c2b-93b3-87d5378940ee","7f1440e1-448e-40bc-b4b3-e25c327f4218"],"price":78,"gender":"male","category":"hoodie"},{"id":"8","name":"Thin Simple Man Hoodie","sale":0,"color":"dark gray","image":["637e67f7-5c68-4104-86f3-fbc7c3c458b8","b0c3eb8c-0ca9-4ba3-961a-b61079e5eeff"],"price":88,"gender":"male","category":"hoodie"},{"id":"9","name":"Thick Designed Man Hoodie","sale":10,"color":"blue","image":["571ced79-2fac-4736-8d62-451626dad6e4","1c6227a2-a310-49d2-952f-9e484e14540d","5be8b9c4-caf2-4cfb-a8f8-eab1be56a7f6","64cdf907-fcb2-43a3-a9c4-98a0b1206827"],"price":104,"gender":"male","category":"hoodie"},{"id":"10","name":"Designed Man Hoodie","sale":0,"color":"black","image":["94bacde2-2205-4599-8498-bf83aedec622","f18cc9f4-29b3-4e6a-b660-942d0ffb3bbd"],"price":74,"gender":"male","category":"hoodie"},{"id":"11","name":"Thin Fancy Man Hoodie","sale":5,"color":"light gray","image":["a7a3798f-017b-46ed-b93c-ceb923f1c18e","db798671-8ae8-4539-aead-0779919c6221","a61eefa1-1f20-45e2-bcff-8e349a0a509f"],"price":144,"gender":"male","category":"hoodie"},{"id":"12","name":"Thick Designed Man Hoodie","sale":0,"color":"yellow","image":["4e2a751a-7800-4aab-92c4-1776daac1fff","aaf4ca8b-29d3-435e-9557-39b16052f7eb","70dce199-a0cf-48d0-9f62-624b3a3b7de2"],"price":68,"gender":"male","category":"hoodie"},{"id":"13","name":"Designed Woman Hoodie","sale":0,"color":"green","image":["81feeece-36f7-463a-9809-5f9277f83e3e","320e2ce1-653e-479f-bbe5-34794058549d"],"price":100,"gender":"female","category":"hoodie"},{"id":"14","name":"Thin Fancy Simple Woman Hoodie","sale":5,"color":"green","image":["128f1efc-db22-4b14-a9d9-338f1519dcb5","c777a96f-27dd-4436-b88c-72942c88b4c7"],"price":124,"gender":"female","category":"hoodie"},{"id":"15","name":"Thick Designed Woman Hoodie","sale":0,"color":"white","image":["fb39efb5-1412-4005-bd63-d817ca7a5436","ac913fbc-5343-4314-9a44-acf1f7de531d"],"price":70,"gender":"female","category":"hoodie"},{"id":"16","name":"Thin Designed Man Hoodie","sale":0,"color":"black","image":["dba43269-065a-4a21-86d5-8343807a8ced","cd7b8271-9b55-4f98-bc43-5f3b0d1439ca"],"price":84,"gender":"male","category":"hoodie"},{"id":"17","name":"Fancy Designed Man Hoodie","sale":5,"color":"red","image":["e7bb614c-01a5-445f-81af-d41bbfff922c","f0d8111b-8fdb-4b48-941f-66252a5cf822","1521a9a3-bb44-4e19-af7f-b53f971766c9"],"price":144,"gender":"male","category":"hoodie"},{"id":"18","name":"Thick Designed Woman Hoodie","sale":0,"color":"orange","image":["924f1641-0759-416b-8758-e14f55b7e8f3","8c251302-9505-46c9-b0c4-bdf6fe8af15c"],"price":74,"gender":"female","category":"hoodie"},{"id":"19","name":"Thick Fancy Designed Woman Hoodie","sale":0,"color":"white","image":["a6ca4445-5f45-49c4-857c-6354c8c15bb9","065f4caf-9e0c-4ddc-b88a-92f476d35e84","84a06a93-4806-44fa-91b6-b7237b46362f"],"price":140,"gender":"female","category":"hoodie"},{"id":"20","name":"Fancy Smooth Woman Hoodie","sale":20,"color":"gray","image":["4696ebe7-79de-48c2-bc80-ad9dee837cf9","e734d754-b065-40a9-90a1-a8c1f16b7038"],"price":180,"gender":"female","category":"hoodie"},{"id":"21","name":"Thin Clean Woman Hoodie","sale":0,"color":"teal","image":["5f73cf2b-04bc-4595-bafb-4d57b8e5e611","6d6f9902-a9a0-493c-9baf-9132967dd97a","f6ae2df0-2a25-486b-a5d7-8305ed37bcd1","e44de336-44bd-4779-9f1e-4524002e1b17"],"price":140,"gender":"female","category":"hoodie"},{"id":"22","name":"Fancy Designed Woman Hoodie","sale":5,"color":"black","image":["fd7f520b-b494-4956-8c45-fe03b19bbd90","667a20a2-1bc1-4712-bac1-fa6f3c0dafdd","f95cabe4-bdda-4c79-8140-95004a4bb8a2"],"price":114,"gender":"female","category":"hoodie"},{"id":"23","name":"Thick Smooth Man Hoodie","sale":5,"color":"brown","image":["68ed4b18-7b7e-4238-aa4a-46756803f61a","b073c624-d883-4028-9cef-2253ce248590","5d5aadae-2b61-4353-ae19-552e3799ae9e"],"price":180,"gender":"male","category":"hoodie"},{"id":"24","name":"Fancy Clean Designed Woman Hoodie","sale":0,"color":"white","image":["7b0c3eb2-482f-4879-821c-2f9f1073d50e","e237c245-bb74-4aac-a32e-727ac5e84170"],"price":220,"gender":"female","category":"hoodie"},{"id":"25","name":"Designed Woman Hoodie","sale":0,"color":"black","image":["32643b11-51c5-4b3e-83a3-1a9b502c6348","a537bab8-3acd-4222-a7d5-f598a8039724","8bfc9953-3e3c-4f60-ae4b-ca9aa3cf995c"],"price":90,"gender":"female","category":"hoodie"}],"sweater":[{"id":"1","name":"Winter Christmas Designed Woman Sweater","sale":0,"color":"red","image":["c640bbf3-9dcf-42db-9c9a-39b3b63b73a4","fc6d87be-e838-4021-a16e-12f02be600ac","ec8151ce-0ba6-4647-82b8-9a0c86adb2ed"],"price":112,"gender":"female","category":"sweater"},{"id":"2","name":"Thin Cable Knit Woman Sweater","sale":0,"color":"red","image":["d2d41f2f-91d2-4acf-80e9-6f86d21d0aa8","d2f4ae25-e9db-44f0-bf2a-ed167a813265","c82ccfe4-8ba5-47a5-b279-44e3603ceb3d"],"price":64,"gender":"female","category":"sweater"},{"id":"3","name":"Aran Woman Sweater","sale":0,"color":"gray","image":["9278fe13-8257-4c86-bd02-c77d480db4f8","3d732ab6-148c-494d-aaa5-6fbeaec6847f"],"price":65,"gender":"female","category":"sweater"},{"id":"4","name":"Aran Crop Top Woman Sweater","sale":0,"color":"dark gray","image":["970f4364-bba2-48e8-815f-d21d36622275","912876d6-07d7-4ff6-9597-393f0614b984"],"price":56,"gender":"female","category":"sweater"},{"id":"5","name":"Thick Aran Man Sweater","sale":10,"color":"green","image":["ae3d15ff-4bfd-413b-8b1f-2c13db0e1437","72af0d86-653c-4738-bc42-7da5c5a5b44a","03b912ce-7959-43e5-be07-3b405b63797b"],"price":114,"gender":"male","category":"sweater"},{"id":"6","name":"Thin Crew Neck Woman Sweater","sale":0,"color":"light gray","image":["c2be122e-954d-46da-9dfd-ff382441cfa7","f6a5ab48-2e9d-424e-b8ee-284e4640c049"],"price":56,"gender":"female","category":"sweater"},{"id":"7","name":"Cowl Simple Woman Sweater","sale":10,"color":"green","image":["4468a1af-7056-48c5-8139-1cf7eb603982","fead3b70-2b00-40e7-bfa8-1d1ffa79a7a0"],"price":124,"gender":"female","category":"sweater"},{"id":"8","name":"Long Neck Cashmere Man Sweater","sale":0,"color":"light gray","image":["43aa4235-5cf9-4711-bdc7-1a845da606d6","2c123e28-616e-4532-91c3-cd31adf61f50"],"price":90,"gender":"male","category":"sweater"},{"id":"9","name":"Overfit Boyfriend Woman Sweater","sale":0,"color":"black","image":["58e252a0-4fd3-4465-9392-7db0a6f53553","3f051aff-0a44-49b6-8893-852538f656d7"],"price":120,"gender":"female","category":"sweater"},{"id":"10","name":"Thin Cable Knit Woman Sweater","sale":0,"color":"red","image":["47da43bc-cb8a-4297-afe1-6e91097a3ca4","9ab802da-5e02-4ca1-976d-df86a1235695"],"price":80,"gender":"female","category":"sweater"},{"id":"11","name":"Winter Christmas Woman Sweater","sale":0,"color":"green","image":["51002c70-4034-4e51-8625-0c649d9aa5ac","eaada9e9-bca2-4a69-b0fe-0283a48b92ba","08cb94cd-a2f4-4809-ba7a-f5d9ecb09b85"],"price":100,"gender":"female","category":"sweater"},{"id":"12","name":"Crew Neck Man Sweater","sale":0,"color":"brown","image":["b0667cf9-1808-4af0-a821-654798235412","a5e9f4c5-f8cf-4959-a10d-ab80cd404800","5f047681-8da6-4e86-b621-8b44a3e6807c"],"price":64,"gender":"male","category":"sweater"},{"id":"13","name":"Mid Boyfriend Woman Sweater","sale":0,"color":"pink","image":["2ced90d4-02b2-4200-bb08-2e13e555412b","8a6b122c-ff25-435b-8d04-a3c3395c7f4d"],"price":70,"gender":"female","category":"sweater"},{"id":"14","name":"Crew Neck Fancy Woman Sweater","sale":10,"color":"red","image":["d0b57913-5b8c-4266-8652-eedcabb9e5d7","fed25ae6-44f4-4019-b76a-90147fa8555f"],"price":140,"gender":"female","category":"sweater"},{"id":"15","name":"Aran Patterned Man Sweater","sale":0,"color":"light brown","image":["4c7fa7b3-be1b-43ae-b077-2b8575c0af23","d35e56f5-e09f-4d81-bcff-5db058915853"],"price":104,"gender":"male","category":"sweater"},{"id":"16","name":"Cable Knit Crop Top Fancy Woman Sweater","sale":10,"color":"begie","image":["c25f347a-1a25-445a-bb0b-53fe9f8b504d","d085794a-6c55-4c6e-ad15-fa2bacbaaa7f","1b596b18-9ded-4a63-bab6-3354b3591a09","8b5c8067-7ef5-46b8-b9f0-2aec62b0b480"],"price":126,"gender":"female","category":"sweater"},{"id":"17","name":"Clean Designed Man to Man Sweater","sale":0,"color":"navy","image":["8793e630-b678-4222-992b-2b076a46ac63","fdfa7f81-2c90-4b5e-95f0-eb1104874fde"],"price":56,"gender":"male","category":"sweater"},{"id":"18","name":"Overfit Crew Neck Fancy Woman Sweater","sale":0,"color":"gray","image":["438e1fae-02bd-4114-9e67-4c5b851f1b93","c56cd815-c3fe-492e-8026-ea9a252e655f","f33a49a7-47fe-4916-88a7-9fe8a834b43c"],"price":156,"gender":"female","category":"sweater"},{"id":"19","name":"Cowl Neck Fancy Woman Sweater","sale":10,"color":"white","image":["9a7a2769-7a17-411f-91f0-764dbac45da9","c8e6fd0b-3eab-4b7d-9427-02e9e0ee040e","ed0bac9a-bc23-4f4c-a447-a15decfc08be","3dec9576-e8ea-4719-92bb-c22ff2b16243"],"price":148,"gender":"female","category":"sweater"},{"id":"20","name":"Thin Cable Knit Woman Sweater","sale":30,"color":"red","image":["3efbaba2-4416-48fb-a954-791c01f7c89a","947f98db-ca6a-4a27-9c8d-ba60b380a5ba"],"price":90,"gender":"female","category":"sweater"},{"id":"21","name":"Cable Knit Three Layer Woman Sweater","sale":0,"color":"mixed","image":["49cb8ff4-226e-463e-86b3-e149e20ed1a5","d0a6436a-fc8d-46ca-8500-5ab85b6f0638"],"price":90,"gender":"female","category":"sweater"},{"id":"22","name":"Cowl Neck Cleaned Fancy Woman Sweater","sale":10,"color":"begie","image":["12b30676-1d91-4ac7-8915-dd8bd832a690","5590cc6b-0a08-4cc7-9495-345b1ad0acc5","41438387-e49b-4a58-896d-ebc1e195953b","3fa42e91-6d49-41a6-b20b-6ddb379660f3"],"price":160,"gender":"female","category":"sweater"},{"id":"23","name":"Mid Cowl Neck Thin Woman Sweater","sale":0,"color":"green","image":["105903d4-48d2-4d6d-a838-11b5dc5879a3","ed751ae2-021e-4ef0-866a-3e3edb5107a0","53b50c3f-2709-4a6a-8e80-82a521b2841d"],"price":98,"gender":"female","category":"sweater"}]}}
